[
  {
    "id": "ORD-001",
    "customerName": "Alice Silva",
    "items": [
      "Artisanal Bread x2",
      "Croissant x3"
    ],
    "total": 24.5,
    "status": "Delivered",
    "createdAt": "2024-01-15T10:30:00.000Z"
  },
  {
    "id": "ORD-002",
    "customerName": "Bob Perera",
    "items": [
      "Chocolate Cake x1"
    ],
    "total": 18,
    "status": "Shipped",
    "createdAt": "2024-01-15T11:45:00.000Z"
  },
  {
    "id": "ORD-003",
    "customerName": "Carol Zhang",
    "items": [
      "Coffee Beans x1",
      "Espresso Cup x2"
    ],
    "total": 45,
    "status": "Delivered",
    "createdAt": "2024-01-14T09:15:00.000Z"
  },
  {
    "id": "ORD-004",
    "customerName": "Damian kennt",
    "items": [
      "Eggs x2",
      "Bread x1"
    ],
    "total": 9,
    "status": "Pending",
    "createdAt": "2026-07-14T12:44:27.820Z"
  }
]